adafruit_pct2075.py
adafruit_circuitpython_pct2075-1.1.26.dist-info/licenses/LICENSE
adafruit_circuitpython_pct2075-1.1.26.dist-info/METADATA
adafruit_circuitpython_pct2075-1.1.26.dist-info/WHEEL
adafruit_circuitpython_pct2075-1.1.26.dist-info/top_level.txt
adafruit_circuitpython_pct2075-1.1.26.dist-info/RECORD
